__init__.py
utils.py
visual_edge.py
visual_graph.py
visual_node.py
visual_graph-0.1.2.dist-info/METADATA
visual_graph-0.1.2.dist-info/WHEEL
visual_graph-0.1.2.dist-info/top_level.txt
visual_graph-0.1.2.dist-info/RECORD
